obscure_password/__init__.py
obscure_password/obscure.py
obscure_password-1.0.3.dist-info/LICENSE.txt
obscure_password-1.0.3.dist-info/METADATA
obscure_password-1.0.3.dist-info/WHEEL
obscure_password-1.0.3.dist-info/top_level.txt
obscure_password-1.0.3.dist-info/RECORD
