Metadata-Version: 2.1
Name: obscure-password
Version: 1.0.3
Summary: Self contained obfuscation of hardcoded passwords in Python scripts.
Home-page: https://github.com/Shapedsundew9/obscure-password
Author: Shaped Sundew
License: UNKNOWN
Project-URL: Bug Reports, https://github.com/Shapedsundew9/obscure-password/issues
Project-URL: Source, https://github.com/Shapedsundew9/obscure-password
Keywords: password,obfuscation,obscure,development
Platform: UNKNOWN
Classifier: Development Status :: 5 - Production/Stable
Classifier: Intended Audience :: Developers
Classifier: Topic :: Software Development :: Libraries :: Python Modules
Classifier: License :: OSI Approved :: MIT License
Classifier: Programming Language :: Python :: 3
Classifier: Programming Language :: Python :: 3.6
Classifier: Programming Language :: Python :: 3.7
Classifier: Programming Language :: Python :: 3.8
Classifier: Programming Language :: Python :: 3.9
Classifier: Programming Language :: Python :: 3 :: Only
Requires-Python: >=3.6, <4
License-File: LICENSE.txt
Provides-Extra: test
Requires-Dist: pytest ; extra == 'test'
